test_release/__init__.py
test_release/_nbdev.py
test_release/core.py
test_release-0.0.1.dist-info/LICENSE
test_release-0.0.1.dist-info/METADATA
test_release-0.0.1.dist-info/WHEEL
test_release-0.0.1.dist-info/entry_points.txt
test_release-0.0.1.dist-info/top_level.txt
test_release-0.0.1.dist-info/RECORD
